LICENSE.txt
MANIFEST.in
README.md
pyproject.toml
requirements.txt
setup.py
Pyfhel/Afhel.pxd
Pyfhel/PyCtxt.cpp
Pyfhel/PyCtxt.pxd
Pyfhel/PyCtxt.pyx
Pyfhel/PyPtxt.cpp
Pyfhel/PyPtxt.pxd
Pyfhel/PyPtxt.pyx
Pyfhel/Pyfhel.cpp
Pyfhel/Pyfhel.pxd
Pyfhel/Pyfhel.pyx
Pyfhel/__init__.py
Pyfhel/iostream.pxd
Pyfhel/test.py
Pyfhel/Afhel/Afhel.h
Pyfhel/Afhel/Afhelib.cpp
Pyfhel/Afhel/Afhelib.h
Pyfhel/Afhel/Afpalisade.cpp
Pyfhel/Afhel/Afpalisade.h
Pyfhel/Afhel/Afseal.cpp
Pyfhel/Afhel/Afseal.h
Pyfhel/Afhel/utils.cpp
Pyfhel/Afhel/utils.h
Pyfhel/SEAL/SEAL/seal/batchencoder.cpp
Pyfhel/SEAL/SEAL/seal/batchencoder.h
Pyfhel/SEAL/SEAL/seal/blake2-impl.h
Pyfhel/SEAL/SEAL/seal/blake2.h
Pyfhel/SEAL/SEAL/seal/blake2b.c
Pyfhel/SEAL/SEAL/seal/blake2xb.c
Pyfhel/SEAL/SEAL/seal/ciphertext.cpp
Pyfhel/SEAL/SEAL/seal/ciphertext.h
Pyfhel/SEAL/SEAL/seal/ckks.cpp
Pyfhel/SEAL/SEAL/seal/ckks.h
Pyfhel/SEAL/SEAL/seal/clang.h
Pyfhel/SEAL/SEAL/seal/clipnormal.cpp
Pyfhel/SEAL/SEAL/seal/clipnormal.h
Pyfhel/SEAL/SEAL/seal/common.cpp
Pyfhel/SEAL/SEAL/seal/common.h
Pyfhel/SEAL/SEAL/seal/config.h
Pyfhel/SEAL/SEAL/seal/context.cpp
Pyfhel/SEAL/SEAL/seal/context.h
Pyfhel/SEAL/SEAL/seal/croots.cpp
Pyfhel/SEAL/SEAL/seal/croots.h
Pyfhel/SEAL/SEAL/seal/decryptor.cpp
Pyfhel/SEAL/SEAL/seal/decryptor.h
Pyfhel/SEAL/SEAL/seal/defines.h
Pyfhel/SEAL/SEAL/seal/dwthandler.h
Pyfhel/SEAL/SEAL/seal/dynarray.h
Pyfhel/SEAL/SEAL/seal/encryptionparams.cpp
Pyfhel/SEAL/SEAL/seal/encryptionparams.h
Pyfhel/SEAL/SEAL/seal/encryptor.cpp
Pyfhel/SEAL/SEAL/seal/encryptor.h
Pyfhel/SEAL/SEAL/seal/evaluator.cpp
Pyfhel/SEAL/SEAL/seal/evaluator.h
Pyfhel/SEAL/SEAL/seal/fips202.c
Pyfhel/SEAL/SEAL/seal/fips202.h
Pyfhel/SEAL/SEAL/seal/galois.cpp
Pyfhel/SEAL/SEAL/seal/galois.h
Pyfhel/SEAL/SEAL/seal/galoiskeys.h
Pyfhel/SEAL/SEAL/seal/gcc.h
Pyfhel/SEAL/SEAL/seal/globals.cpp
Pyfhel/SEAL/SEAL/seal/globals.h
Pyfhel/SEAL/SEAL/seal/gsl.h
Pyfhel/SEAL/SEAL/seal/gsl_algorithm.h
Pyfhel/SEAL/SEAL/seal/gsl_assert.h
Pyfhel/SEAL/SEAL/seal/gsl_byte.h
Pyfhel_CKKS.egg-info/PKG-INFO
Pyfhel_CKKS.egg-info/SOURCES.txt
Pyfhel_CKKS.egg-info/dependency_links.txt
Pyfhel_CKKS.egg-info/not-zip-safe
Pyfhel_CKKS.egg-info/requires.txt
Pyfhel_CKKS.egg-info/top_level.txt
