Metadata-Version: 2.1
Name: Pyfhel-CKKS
Version: 3.0.3
Summary: Python for Homomorphic Encryption Libraries
Home-page: https://github.com/MarbleHE/Pyfhel-CKKS
Author: Alberto Ibarrondo, Alexander Viand
Author-email: ibarrond@eurecom.fr, alexander.viand@inf.ethz.ch
License: GNU GPLv3
Keywords: homomorphic encryption cython cryptography
Platform: UNKNOWN
Classifier: Programming Language :: C++
Classifier: Programming Language :: Cython
Classifier: Programming Language :: Python :: 3
Classifier: Programming Language :: Python :: 3.5
Classifier: Programming Language :: Python :: 3.6
Classifier: Programming Language :: Python :: 3.7
Classifier: Programming Language :: Python :: 3.8
Classifier: Programming Language :: Python :: Implementation :: CPython
Classifier: Development Status :: 5 - Production/Stable
Classifier: License :: OSI Approved :: GNU General Public License v3 (GPLv3)
Classifier: Operating System :: Unix
Classifier: Operating System :: POSIX
Classifier: Operating System :: Microsoft :: Windows
Classifier: Topic :: Security
Classifier: Topic :: Security :: Cryptography
License-File: LICENSE.txt
